<?xml version = '1.0' encoding = 'UTF-8'?>
<TableProxyOraclev20c class="oracle.dbtools.crest.model.design.storage.oracle.v20c.TableProxyOraclev20c" name="class_teacher" directorySegmentName="seg_0" id="B10E45F4-81E2-D01B-B343-595A6EA3332C">
<createdBy>msimonz</createdBy>
<createdTime>2026-02-27 19:45:52 UTC</createdTime>
<ownerDesignName>DER_EDIT</ownerDesignName>
<logging>YES</logging>
<partitionedRowMovement>DISABLE</partitionedRowMovement>
<temporaryChanged>false</temporaryChanged>
<accessDriverType>oracle_loader</accessDriverType>
<rejectLimit></rejectLimit>
<columnProxies itemClass="oracle.dbtools.crest.model.design.storage.oracle.v12c.ColumnProxyOraclev12c">
<ColumnProxy name="id_class" id="33ED9D3B-A875-66A0-2F2E-0403191CB101">
<createdBy>msimonz</createdBy>
<createdTime>2026-02-27 19:45:52 UTC</createdTime>
<ownerDesignName>DER_EDIT</ownerDesignName>
</ColumnProxy>
<ColumnProxy name="id_teacher" id="E1DC1D47-0489-5E00-3348-F52A6805E6A1">
<createdBy>msimonz</createdBy>
<createdTime>2026-02-27 19:45:52 UTC</createdTime>
<ownerDesignName>DER_EDIT</ownerDesignName>
</ColumnProxy>
<ColumnProxy name="created_at" id="FCCE7F65-21F5-C96B-AB3F-6716A17C703D">
<createdBy>msimonz</createdBy>
<createdTime>2026-02-27 19:45:52 UTC</createdTime>
<ownerDesignName>DER_EDIT</ownerDesignName>
<defaultValue>SYSTIMESTAMP</defaultValue>
</ColumnProxy>
</columnProxies>
<foreignKeys>
<ForeignKey class="oracle.dbtools.crest.model.design.storage.oracle.v10g.FKProxyOraclev10g" name="fk_ct_teacher" id="6D9A24A3-E68D-5BCD-215B-38A8F466180C">
<createdBy>msimonz</createdBy>
<createdTime>2026-02-27 19:45:52 UTC</createdTime>
<ownerDesignName>DER_EDIT</ownerDesignName>
</ForeignKey>
<ForeignKey class="oracle.dbtools.crest.model.design.storage.oracle.v10g.FKProxyOraclev10g" name="fk_ct_class" id="D5F54919-9CAF-10FF-2E1B-22868B15574A">
<createdBy>msimonz</createdBy>
<createdTime>2026-02-27 19:45:52 UTC</createdTime>
<ownerDesignName>DER_EDIT</ownerDesignName>
</ForeignKey>
</foreignKeys>
<primaryKeys>
<PrimaryKey class="oracle.dbtools.crest.model.design.storage.oracle.v10g.PKProxyOraclev10g" name="pk_class_teacher" id="9289C2CA-67FD-EBD0-569B-1CD45873A8C2">
<createdBy>msimonz</createdBy>
<createdTime>2026-02-27 19:45:52 UTC</createdTime>
<ownerDesignName>DER_EDIT</ownerDesignName>
<indexSort>SORTED</indexSort>
</PrimaryKey>
</primaryKeys>
</TableProxyOraclev20c>
